audiocencesored/__init__.py
audiocencesored/audio_stamp.py
audiocencesored/get_list.py
audiocencesored/get_rating.py
audiocencesored/get_wordlist.py
audiocencesored-0.2.dist-info/METADATA
audiocencesored-0.2.dist-info/WHEEL
audiocencesored-0.2.dist-info/top_level.txt
audiocencesored-0.2.dist-info/RECORD
