Metadata-Version: 2.1
Name: audiocencesored
Version: 0.2
Summary: Check your audio for profanity on steroids.
Home-page: https://github.com/sleepingcat4/audio-profanity
Author: Sleeping4cat i.e. Ammar
Author-email: sleeping4cat@gmail.com
Classifier: Programming Language :: Python :: 3.10
Classifier: License :: OSI Approved :: MIT License
Classifier: Operating System :: OS Independent
Requires-Dist: openai-whisper
Requires-Dist: setuptools-rust
